hooklet/__init__.py
hooklet/base/__init__.py
hooklet/base/node.py
hooklet/base/pilot.py
hooklet/base/types.py
hooklet/logger/__init__.py
hooklet/logger/hooklet_logger.py
hooklet/logger/node_logger.py
hooklet/node/__init__.py
hooklet/node/emitter.py
hooklet/node/pipe.py
hooklet/node/rpc.py
hooklet/node/sinker.py
hooklet/node/worker.py
hooklet/pilot/__init__.py
hooklet/pilot/inproc_pilot.py
hooklet/pilot/nats_pilot.py
hooklet/pilot/zmq_pilot.py
hooklet/utils/__init__.py
hooklet/utils/id_generator.py
hooklet-0.5.8.dist-info/licenses/LICENSE
hooklet-0.5.8.dist-info/METADATA
hooklet-0.5.8.dist-info/WHEEL
hooklet-0.5.8.dist-info/top_level.txt
hooklet-0.5.8.dist-info/RECORD
