Metadata-Version: 2.4
Name: hooklet
Version: 0.5.8
Summary: An asynchronous, event-driven Python framework using NATS messaging system
Author-email: Yite <coastq22889@icloud.com>
License-Expression: MIT
Classifier: Programming Language :: Python :: 3.12
Classifier: Operating System :: OS Independent
Classifier: Development Status :: 3 - Alpha
Classifier: Intended Audience :: Developers
Requires-Python: >=3.12
License-File: LICENSE
Requires-Dist: nats-py>=2.3.1
Requires-Dist: PyYAML>=6.0
Requires-Dist: pyzmq>=26.4.0
Provides-Extra: dev
Requires-Dist: pytest>=7.0.0; extra == "dev"
Requires-Dist: pytest-asyncio>=0.18.3; extra == "dev"
Requires-Dist: black; extra == "dev"
Requires-Dist: isort; extra == "dev"
Dynamic: license-file
